setup.cfg
setup.py
osmread/__init__.py
osmread/elements.py
osmread/script.py
osmread.egg-info/PKG-INFO
osmread.egg-info/SOURCES.txt
osmread.egg-info/dependency_links.txt
osmread.egg-info/entry_points.txt
osmread.egg-info/not-zip-safe
osmread.egg-info/requires.txt
osmread.egg-info/top_level.txt
osmread/parser/__init__.py
osmread/parser/pbf.py
osmread/parser/xml.py
osmread/protobuf/__init__.py
osmread/protobuf/fileformat_pb2.py
osmread/protobuf/osm_pb2.py
osmread/protobuf/osmformat_pb2.py