Metadata-Version: 1.1
Name: osmread
Version: 0.2
Summary: Simple library for reading OpenStreetMap XML and PBF data files
Home-page: http://github.com/dezhin/osmread
Author: Aleksandr Dezhin
Author-email: me@dezhin.net
License: MIT License
Platform: UNKNOWN
Classifier: Development Status :: 4 - Beta
Classifier: Operating System :: OS Independent
Classifier: License :: OSI Approved :: MIT License
Classifier: Programming Language :: Python :: 2.7
Classifier: Programming Language :: Python :: 3
Classifier: Topic :: Software Development :: Libraries
Classifier: Topic :: Scientific/Engineering :: GIS
